rodos/__init__.py
rodos/checksums.py
rodos/gateway.py
rodos/linkinterface.py
rodos/linkinterfaceUART.py
rodos/linkinterfaceudp.py
rodos/networkmessage.py
rodos/printTopic.py
rodos/topic.py
rodos-0.1.1.dist-info/METADATA
rodos-0.1.1.dist-info/WHEEL
rodos-0.1.1.dist-info/top_level.txt
rodos-0.1.1.dist-info/RECORD
