Metadata-Version: 2.1
Name: rodos
Version: 0.1.1
Summary: rodos middleware in python
Author: ['Sebastian Kind']
Requires-Dist: pyserial
